pyventory/__init__.py
pyventory/assets.py
pyventory/base.py
pyventory/errors.py
pyventory/export.py
pyventory/py.typed
pyventory-3.3.2.dist-info/LICENSE
pyventory-3.3.2.dist-info/WHEEL
pyventory-3.3.2.dist-info/METADATA
pyventory-3.3.2.dist-info/RECORD
