Metadata-Version: 2.1
Name: pyventory
Version: 3.3.2
Summary: Ansible Inventory implementation that uses Python syntax
Home-page: https://github.com/lig/pyventory
License: MIT
Keywords: devops,ansible,inventory,terraform,vars
Author: Serge Matveenko
Author-email: lig@countzero.co
Requires-Python: >=3.10,<4.0
Classifier: Development Status :: 5 - Production/Stable
Classifier: Intended Audience :: Developers
Classifier: Intended Audience :: System Administrators
Classifier: License :: OSI Approved :: MIT License
Classifier: Programming Language :: Python :: 3
Classifier: Programming Language :: Python :: 3.10
Classifier: Programming Language :: Python :: 3.11
Classifier: Topic :: System :: Systems Administration
Requires-Dist: attrs (>=22.1.0,<23.0.0)
Requires-Dist: ordered-set (>=4.0.2,<5.0.0)
Project-URL: Documentation, https://readthedocs.org/projects/pyventory/
Project-URL: Repository, https://github.com/lig/pyventory.git
